bixr/__init__.py
bixr/api.py
bixr/llapi.py
bixr-0.0.2.dist-info/LICENSE
bixr-0.0.2.dist-info/METADATA
bixr-0.0.2.dist-info/WHEEL
bixr-0.0.2.dist-info/top_level.txt
bixr-0.0.2.dist-info/RECORD
