Metadata-Version: 2.1
Name: bixr
Version: 0.0.2
Summary: Banca d'Italia eXchange Rates
Home-page: https://github.com/riccz/bixr
Author: Riccardo Zanol
Author-email: rz@riccza.nl
Project-URL: Bug Tracker, https://github.com/riccz/bixr/issues
Classifier: Programming Language :: Python :: 3
Classifier: License :: OSI Approved :: MIT License
Classifier: Operating System :: OS Independent
Requires-Python: >=3.6
License-File: LICENSE
Requires-Dist: requests
Requires-Dist: requests-cache
Provides-Extra: pandas
Requires-Dist: pandas ; extra == 'pandas'
